mbti_personality_prediction/__init__.py
mbti_personality_prediction-1.0.0.dist-info/LICENSE
mbti_personality_prediction-1.0.0.dist-info/METADATA
mbti_personality_prediction-1.0.0.dist-info/WHEEL
mbti_personality_prediction-1.0.0.dist-info/top_level.txt
mbti_personality_prediction-1.0.0.dist-info/RECORD
