Metadata-Version: 2.1
Name: mbti-personality-prediction
Version: 1.0.0
Summary: Predicts MBTI personality type from one's writing style through Linguistic Inquiry and Word Count
Home-page: https://github.com/rvmendillo/mbti_personality_prediction
Author: Rey Victor Mendillo
Author-email: admin@rvmendillo.com
License: UNKNOWN
Project-URL: Bug Tracker, https://github.com/rvmendillo/mbti_personality_prediction/issues
Platform: UNKNOWN
Classifier: Programming Language :: Python :: 3
Classifier: License :: OSI Approved :: MIT License
Classifier: Operating System :: OS Independent
Classifier: Natural Language :: English
Classifier: Topic :: Scientific/Engineering :: Artificial Intelligence
Classifier: Topic :: Scientific/Engineering :: Medical Science Apps.
Classifier: Topic :: Text Processing
Requires-Python: >=3.6
License-File: LICENSE
Requires-Dist: pandas
Requires-Dist: liwc
Requires-Dist: nltk
